[[{"__type__":"cc.SceneAsset","_name":"mainScene","scene":{"__id__":1},"asyncLoadAssets":null},{"__type__":"cc.Scene","_name":"New Node","_children":[{"__id__":2}],"_active":false,"_anchorPoint":{"__type__":"cc.Vec2"},"autoReleaseAssets":false},{"__type__":"cc.Node","_name":"Canvas","_parent":{"__id__":1},"_children":[{"__id__":3},{"__id__":4},{"__id__":5},{"__id__":6},{"__id__":7}],"_level":1,"_components":[{"__type__":"cc.Canvas","node":{"__id__":2},"_designResolution":{"__type__":"cc.Size","width":750,"height":1334},"_fitWidth":true,"_fitHeight":false},{"__type__":"658dcTqCq1EsYsnCLnPmDep","node":{"__id__":2},"nodRule":{"__id__":46},"nodView":{"__id__":6},"lblOne":{"__id__":22},"lblTwo":{"__id__":25},"lblThree":{"__id__":28},"lblBalance":{"__id__":32},"ctrl":{"__id__":18},"nodOpen":{"__id__":87},"moreLayer":{"__id__":64},"rankLayer":{"__id__":65}}],"_contentSize":{"__type__":"cc.Size","width":750,"height":1334},"_position":{"__type__":"cc.Vec3","x":375,"y":667},"_id":"5a90i9fY9KjYYi5GfuppTr"},{"__type__":"cc.Node","_name":"Main Camera","_parent":{"__id__":2},"_level":2,"_components":[{"__type__":"cc.Camera","node":{"__id__":3},"_cullingMask":1,"_clearFlags":7,"_depth":-1}],"_position":{"__type__":"cc.Vec3","z":525.6774200971543}},{"__type__":"cc.Node","_name":"dialog","_parent":{"__id__":2},"_level":2,"_components":[{"__type__":"cc.Camera","node":{"__id__":4},"_cullingMask":2,"_depth":2,"_nearClip":0.1}],"_position":{"__type__":"cc.Vec3","z":525.6774200971543}},{"__type__":"cc.Node","_name":"box","_parent":{"__id__":2},"_level":2,"_components":[{"__type__":"cc.Camera","node":{"__id__":5},"_cullingMask":4,"_nearClip":0.1}],"_position":{"__type__":"cc.Vec3","z":525.6774200971543}},{"__type__":"cc.Node","_name":"spr_bg","_parent":{"__id__":2},"_level":2,"_components":[{"__type__":"cc.Sprite","node":{"__id__":6},"_materials":[{"__uuid__":"ecpdLyjvZBwrvm+cedCcQy"}],"_spriteFrame":{"__uuid__":"61Gn50AvtGxJthnG9MJ5zp"}},{"__type__":"bd263DD+AdO15fKqN3ATgQv","node":{"__id__":6}}],"_contentSize":{"__type__":"cc.Size","width":750,"height":1334}},{"__type__":"cc.Node","_name":"nod_main","_parent":{"__id__":2},"_children":[{"__id__":8},{"__id__":9},{"__id__":19},{"__id__":37},{"__id__":39},{"__id__":46},{"__id__":51},{"__id__":65},{"__id__":78},{"__id__":89},{"__id__":101},{"__id__":115}],"_level":2,"_components":[{"__type__":"cc.Widget","node":{"__id__":7},"_alignFlags":1}],"_position":{"__type__":"cc.Vec3","y":667}},{"__type__":"cc.Node","_name":"bg","_parent":{"__id__":7},"_level":2,"_components":[{"__type__":"cc.Sprite","node":{"__id__":8},"_materials":[{"__uuid__":"ecpdLyjvZBwrvm+cedCcQy"}],"_spriteFrame":{"__uuid__":"7anGq1mEBLJISv9KaLKCpF"}}],"_contentSize":{"__type__":"cc.Size","width":730,"height":1055},"_position":{"__type__":"cc.Vec3","y":-804.465}},{"__type__":"cc.Node","_name":"top","_parent":{"__id__":7},"_children":[{"__id__":10}],"_level":2,"_position":{"__type__":"cc.Vec3","y":-508.151}},{"__type__":"cc.Node","_name":"scr","_parent":{"__id__":9},"_children":[{"__id__":11},{"__id__":14},{"__id__":15},{"__id__":16},{"__id__":17}],"_level":3,"_components":[{"__id__":18}],"_contentSize":{"__type__":"cc.Size","width":475,"height":150},"_position":{"__type__":"cc.Vec3","y":-1.216}},{"__type__":"cc.Node","_name":"itemTemp","_parent":{"__id__":10},"_children":[{"__id__":12},{"__id__":13}],"_level":4,"_components":[{"__type__":"cc.Sprite","node":{"__id__":11},"_materials":[{"__uuid__":"ecpdLyjvZBwrvm+cedCcQy"}],"_spriteFrame":{"__uuid__":"a96oO0eiZGDIsw6ZzGWPD0"}}],"_contentSize":{"__type__":"cc.Size","width":149,"height":148}},{"__type__":"cc.Node","_name":"spr_m","_parent":{"__id__":11},"_level":5,"_components":[{"__type__":"cc.Sprite","node":{"__id__":12},"_materials":[{"__uuid__":"ecpdLyjvZBwrvm+cedCcQy"}],"_spriteFrame":{"__uuid__":"8c20Sso/ZEn7NUfNSM+EBh"},"_sizeMode":0}],"_contentSize":{"__type__":"cc.Size","width":90,"height":90},"_position":{"__type__":"cc.Vec3","y":19.14}},{"__type__":"cc.Node","_name":"lbl_name","_parent":{"__id__":11},"_level":1,"_components":[{"__type__":"cc.Label","node":{"__id__":13},"_materials":[{"__uuid__":"ecpdLyjvZBwrvm+cedCcQy"}],"_useOriginalSize":false,"_string":"华为 P40 Pro","_N$string":"华为 P40 Pro","_fontSize":20,"_lineHeight":20,"_N$horizontalAlign":1,"_N$verticalAlign":1}],"_color":{"__type__":"cc.Color","r":83,"g":58,"b":3},"_contentSize":{"__type__":"cc.Size","width":117.82,"height":25.2},"_position":{"__type__":"cc.Vec3","y":-46}},{"__type__":"cc.Node","_name":"mask","_parent":{"__id__":10},"_level":3,"_components":[{"__type__":"cc.Mask","node":{"__id__":14},"_materials":[{"__uuid__":"ecpdLyjvZBwrvm+cedCcQy"}]}],"_contentSize":{"__type__":"cc.Size","width":475,"height":150}},{"__type__":"cc.Node","_name":"btn_left copy","_parent":{"__id__":10},"_level":3,"_components":[{"__type__":"cc.Sprite","node":{"__id__":15},"_materials":[{"__uuid__":"ecpdLyjvZBwrvm+cedCcQy"}],"_spriteFrame":{"__uuid__":"a2CSgRQppGF7s1Ul89vTBy"}},{"__type__":"cc.Button","node":{"__id__":15},"clickEvents":[{"__type__":"cc.ClickEvent","target":{"__id__":10},"_componentId":"fe30cIKgMVEZorFzuVDoGsT","handler":"scrollToLeft"}]}],"_contentSize":{"__type__":"cc.Size","width":36,"height":40},"_position":{"__type__":"cc.Vec3","x":-295.055}},{"__type__":"cc.Node","_name":"btn_left copy","_parent":{"__id__":10},"_level":3,"_components":[{"__type__":"cc.Sprite","node":{"__id__":16},"_materials":[{"__uuid__":"ecpdLyjvZBwrvm+cedCcQy"}],"_spriteFrame":{"__uuid__":"a2CSgRQppGF7s1Ul89vTBy"}},{"__type__":"cc.Button","node":{"__id__":16},"clickEvents":[{"__type__":"cc.ClickEvent","target":{"__id__":10},"_componentId":"fe30cIKgMVEZorFzuVDoGsT","handler":"scrollToRight"}]}],"_contentSize":{"__type__":"cc.Size","width":36,"height":40},"_position":{"__type__":"cc.Vec3","x":281.656},"_scale":{"__type__":"cc.Vec3","x":-1,"y":1,"z":1}},{"__type__":"cc.Node","_name":"btn_more","_parent":{"__id__":10},"_level":4,"_components":[{"__type__":"cc.Sprite","node":{"__id__":17},"_materials":[{"__uuid__":"ecpdLyjvZBwrvm+cedCcQy"}],"_spriteFrame":{"__uuid__":"d3hzu+CSdEaJfMNeNdMhzQ"}},{"__type__":"cc.Button","node":{"__id__":17},"clickEvents":[{"__type__":"cc.ClickEvent","target":{"__id__":2},"_componentId":"658dcTqCq1EsYsnCLnPmDep","handler":"onBtnMoreLayer"}]}],"_contentSize":{"__type__":"cc.Size","width":79,"height":97},"_position":{"__type__":"cc.Vec3","x":266.8,"y":106.929}},{"__type__":"fe30cIKgMVEZorFzuVDoGsT","node":{"__id__":10},"content":{"__id__":14},"deltaX":160},{"__type__":"cc.Node","_name":"bottom","_parent":{"__id__":7},"_children":[{"__id__":20},{"__id__":23},{"__id__":26},{"__id__":29},{"__id__":33}],"_level":2,"_position":{"__type__":"cc.Vec3","y":-1189.829}},{"__type__":"cc.Node","_name":"btn_left","_parent":{"__id__":19},"_children":[{"__id__":21}],"_level":3,"_components":[{"__type__":"cc.Sprite","node":{"__id__":20},"_materials":[{"__uuid__":"ecpdLyjvZBwrvm+cedCcQy"}],"_spriteFrame":{"__uuid__":"64FZteYtdPvZghjKwhqHni"}},{"__type__":"cc.Button","node":{"__id__":20},"clickEvents":[{"__type__":"cc.ClickEvent","target":{"__id__":2},"_componentId":"658dcTqCq1EsYsnCLnPmDep","handler":"onBtnOne"}]}],"_contentSize":{"__type__":"cc.Size","width":157,"height":73},"_position":{"__type__":"cc.Vec3","x":-251.053,"y":6.973}},{"__type__":"cc.Node","_name":"desc","_parent":{"__id__":20},"_level":4,"_components":[{"__id__":22}],"_color":{"__type__":"cc.Color","r":164,"g":98,"b":27},"_contentSize":{"__type__":"cc.Size","width":78.41,"height":49.72},"_position":{"__type__":"cc.Vec3","y":10.411}},{"__type__":"cc.Label","node":{"__id__":21},"_materials":[{"__uuid__":"ecpdLyjvZBwrvm+cedCcQy"}],"_useOriginalSize":false,"_string":"20000开1盒","_N$string":"20000开1盒","_fontSize":22,"_lineHeight":22,"_N$horizontalAlign":1,"_N$verticalAlign":1,"_N$overflow":3},{"__type__":"cc.Node","_name":"btn_right","_parent":{"__id__":19},"_children":[{"__id__":24}],"_level":3,"_components":[{"__type__":"cc.Sprite","node":{"__id__":23},"_materials":[{"__uuid__":"ecpdLyjvZBwrvm+cedCcQy"}],"_spriteFrame":{"__uuid__":"f8ny85etpIXLMvPL/ISfvv"}},{"__type__":"cc.Button","node":{"__id__":23},"clickEvents":[{"__type__":"cc.ClickEvent","target":{"__id__":2},"_componentId":"658dcTqCq1EsYsnCLnPmDep","handler":"onBtnTwo"}]}],"_contentSize":{"__type__":"cc.Size","width":157,"height":73},"_position":{"__type__":"cc.Vec3","x":245.844,"y":4.477}},{"__type__":"cc.Node","_name":"desc","_parent":{"__id__":23},"_level":4,"_components":[{"__id__":25}],"_color":{"__type__":"cc.Color","r":164,"g":98,"b":27},"_contentSize":{"__type__":"cc.Size","width":78.41,"height":49.72},"_position":{"__type__":"cc.Vec3","y":10.411}},{"__type__":"cc.Label","node":{"__id__":24},"_materials":[{"__uuid__":"ecpdLyjvZBwrvm+cedCcQy"}],"_useOriginalSize":false,"_string":"20000开1盒","_N$string":"20000开1盒","_fontSize":22,"_lineHeight":22,"_N$horizontalAlign":1,"_N$verticalAlign":1,"_N$overflow":3},{"__type__":"cc.Node","_name":"btn_middle","_parent":{"__id__":19},"_children":[{"__id__":27}],"_level":3,"_components":[{"__type__":"cc.Sprite","node":{"__id__":26},"_materials":[{"__uuid__":"ecpdLyjvZBwrvm+cedCcQy"}],"_spriteFrame":{"__uuid__":"f80CB2QLJLRLtV//drChiJ"}},{"__type__":"cc.Button","node":{"__id__":26},"clickEvents":[{"__type__":"cc.ClickEvent","target":{"__id__":2},"_componentId":"658dcTqCq1EsYsnCLnPmDep","handler":"onBtnThree"}]}],"_contentSize":{"__type__":"cc.Size","width":301,"height":95},"_position":{"__type__":"cc.Vec3","y":4.477}},{"__type__":"cc.Node","_name":"desc","_parent":{"__id__":26},"_level":4,"_components":[{"__id__":28}],"_color":{"__type__":"cc.Color","r":164,"g":98,"b":27},"_contentSize":{"__type__":"cc.Size","width":180,"height":37.8},"_position":{"__type__":"cc.Vec3","y":24.411}},{"__type__":"cc.Label","node":{"__id__":27},"_materials":[{"__uuid__":"ecpdLyjvZBwrvm+cedCcQy"}],"_useOriginalSize":false,"_string":"20000开1盒","_N$string":"20000开1盒","_fontSize":30,"_lineHeight":30,"_N$horizontalAlign":1,"_N$verticalAlign":1,"_N$overflow":3},{"__type__":"cc.Node","_name":"New Sprite","_parent":{"__id__":19},"_children":[{"__id__":30},{"__id__":31}],"_level":3,"_components":[{"__type__":"cc.Sprite","node":{"__id__":29},"_materials":[{"__uuid__":"ecpdLyjvZBwrvm+cedCcQy"}],"_spriteFrame":{"__uuid__":"0eg8OUw99MW62ZChTbW/Zm"}}],"_contentSize":{"__type__":"cc.Size","width":304,"height":44},"_position":{"__type__":"cc.Vec3","x":-165.413,"y":-105.68}},{"__type__":"cc.Node","_name":"New Sprite","_parent":{"__id__":29},"_level":4,"_components":[{"__type__":"cc.Sprite","node":{"__id__":30},"_materials":[{"__uuid__":"ecpdLyjvZBwrvm+cedCcQy"}],"_spriteFrame":{"__uuid__":"73e5Bxt3NI7bewZbEaeEj7"}}],"_contentSize":{"__type__":"cc.Size","width":26,"height":28},"_position":{"__type__":"cc.Vec3","x":-115.764,"y":1.395}},{"__type__":"cc.Node","_name":"lbl_balance","_parent":{"__id__":29},"_level":4,"_components":[{"__id__":32}],"_contentSize":{"__type__":"cc.Size","width":86.76,"height":32.76},"_anchorPoint":{"__type__":"cc.Vec2","y":0.5},"_position":{"__type__":"cc.Vec3","x":-87.539}},{"__type__":"cc.Label","node":{"__id__":31},"_materials":[{"__uuid__":"ecpdLyjvZBwrvm+cedCcQy"}],"_useOriginalSize":false,"_string":"600000","_N$string":"600000","_fontSize":26,"_lineHeight":26,"_N$horizontalAlign":1,"_N$verticalAlign":1},{"__type__":"cc.Node","_name":"btn_change","_parent":{"__id__":19},"_children":[{"__id__":34},{"__id__":35}],"_level":3,"_components":[{"__type__":"cc.Button","node":{"__id__":33},"clickEvents":[{"__type__":"cc.ClickEvent","target":{"__id__":36},"_componentId":"3227ef/7dRM5Y8eMslaWbOC","handler":"change"}],"_N$normalColor":{"__type__":"cc.Color","r":230,"g":230,"b":230},"_N$pressedColor":{"__type__":"cc.Color","r":200,"g":200,"b":200},"pressedColor":{"__type__":"cc.Color","r":200,"g":200,"b":200},"_N$disabledColor":{"__type__":"cc.Color","r":120,"g":120,"b":120,"a":200},"_N$normalSprite":{"__uuid__":"f0BIwQ8D5Ml7nTNQbh1YlS"},"_N$pressedSprite":{"__uuid__":"e97GVMl6JHh5Ml5qEDdSGa"},"pressedSprite":{"__uuid__":"e97GVMl6JHh5Ml5qEDdSGa"},"_N$hoverSprite":{"__uuid__":"f0BIwQ8D5Ml7nTNQbh1YlS"},"hoverSprite":{"__uuid__":"f0BIwQ8D5Ml7nTNQbh1YlS"},"_N$disabledSprite":{"__uuid__":"29FYIk+N1GYaeWH/q1NxQO"}},{"__type__":"cc.Layout","node":{"__id__":33},"_layoutSize":{"__type__":"cc.Size","width":109,"height":40},"_resize":1,"_N$layoutType":1,"_N$spacingX":7}],"_contentSize":{"__type__":"cc.Size","width":109,"height":40},"_position":{"__type__":"cc.Vec3","x":249.479,"y":-108.668}},{"__type__":"cc.Node","_name":"New Sprite","_parent":{"__id__":33},"_level":4,"_components":[{"__type__":"cc.Sprite","node":{"__id__":34},"_materials":[{"__uuid__":"ecpdLyjvZBwrvm+cedCcQy"}],"_spriteFrame":{"__uuid__":"eesohjmCxAzb7e7ZvS7VJp"}}],"_contentSize":{"__type__":"cc.Size","width":36,"height":30},"_position":{"__type__":"cc.Vec3","x":-36.5,"y":-1}},{"__type__":"cc.Node","_name":"New Label","_parent":{"__id__":33},"_level":4,"_components":[{"__type__":"cc.Label","node":{"__id__":35},"_materials":[{"__uuid__":"ecpdLyjvZBwrvm+cedCcQy"}],"_useOriginalSize":false,"_string":"换一批","_N$string":"换一批","_fontSize":22,"_lineHeight":22,"_N$horizontalAlign":1,"_N$verticalAlign":1}],"_contentSize":{"__type__":"cc.Size","width":66,"height":27.72},"_position":{"__type__":"cc.Vec3","x":21.5,"y":1}},{"__type__":"cc.Node","_name":"New Layout","_parent":{"__id__":37},"_level":3,"_components":[{"__type__":"cc.Sprite","node":{"__id__":36},"_materials":[{"__uuid__":"ecpdLyjvZBwrvm+cedCcQy"}],"_type":1,"_sizeMode":0},{"__type__":"cc.Layout","node":{"__id__":36},"_layoutSize":{"__type__":"cc.Size","width":544,"height":134},"_resize":1,"_N$layoutType":3,"_N$spacingX":2,"_N$verticalDirection":0},{"__type__":"3227ef/7dRM5Y8eMslaWbOC","node":{"__id__":36},"boxItem":{"__uuid__":"e121qXN6pMqKoGZmvARduw"}}],"_contentSize":{"__type__":"cc.Size","width":544,"height":134},"_position":{"__type__":"cc.Vec3","y":-128.921}},{"__type__":"cc.Node","_name":"mid","_parent":{"__id__":7},"_children":[{"__id__":38},{"__id__":36}],"_level":2,"_position":{"__type__":"cc.Vec3","y":-712.534}},{"__type__":"cc.Node","_name":"New Sprite","_parent":{"__id__":37},"_level":3,"_components":[{"__type__":"cc.Sprite","node":{"__id__":38},"_materials":[{"__uuid__":"ecpdLyjvZBwrvm+cedCcQy"}],"_spriteFrame":{"__uuid__":"bbwSQ+xvxNrqZS0u/Viz0D"}}],"_contentSize":{"__type__":"cc.Size","width":616,"height":492},"_position":{"__type__":"cc.Vec3","y":-124.808}},{"__type__":"cc.Node","_name":"side","_parent":{"__id__":7},"_children":[{"__id__":40},{"__id__":42},{"__id__":44}],"_level":2,"_position":{"__type__":"cc.Vec3","x":375,"y":-558.25}},{"__type__":"cc.Node","_name":"btn_rule","_parent":{"__id__":39},"_children":[{"__id__":41}],"_level":3,"_components":[{"__type__":"cc.Sprite","node":{"__id__":40},"_materials":[{"__uuid__":"ecpdLyjvZBwrvm+cedCcQy"}],"_spriteFrame":{"__uuid__":"56BCNST/1HKZSMhWXV1CKM"}},{"__type__":"cc.Button","node":{"__id__":40},"clickEvents":[{"__type__":"cc.ClickEvent","target":{"__id__":2},"_componentId":"658dcTqCq1EsYsnCLnPmDep","handler":"onBtnRule"}]}],"_contentSize":{"__type__":"cc.Size","width":80,"height":57},"_anchorPoint":{"__type__":"cc.Vec2","x":1,"y":0.5}},{"__type__":"cc.Node","_name":"New Label","_parent":{"__id__":40},"_level":4,"_components":[{"__type__":"cc.Label","node":{"__id__":41},"_materials":[{"__uuid__":"ecpdLyjvZBwrvm+cedCcQy"}],"_useOriginalSize":false,"_string":"规则","_N$string":"规则","_fontSize":22,"_lineHeight":22,"_N$horizontalAlign":1,"_N$verticalAlign":1}],"_contentSize":{"__type__":"cc.Size","width":44,"height":27.72},"_position":{"__type__":"cc.Vec3","x":-33.474}},{"__type__":"cc.Node","_name":"btn_rank","_parent":{"__id__":39},"_children":[{"__id__":43}],"_level":3,"_components":[{"__type__":"cc.Sprite","node":{"__id__":42},"_materials":[{"__uuid__":"ecpdLyjvZBwrvm+cedCcQy"}],"_spriteFrame":{"__uuid__":"56BCNST/1HKZSMhWXV1CKM"}},{"__type__":"cc.Button","node":{"__id__":42},"clickEvents":[{"__type__":"cc.ClickEvent","target":{"__id__":2},"_componentId":"658dcTqCq1EsYsnCLnPmDep","handler":"onBtnRankLayer"}]}],"_contentSize":{"__type__":"cc.Size","width":80,"height":57},"_anchorPoint":{"__type__":"cc.Vec2","x":1,"y":0.5},"_position":{"__type__":"cc.Vec3","y":-67}},{"__type__":"cc.Node","_name":"New Label","_parent":{"__id__":42},"_level":4,"_components":[{"__type__":"cc.Label","node":{"__id__":43},"_materials":[{"__uuid__":"ecpdLyjvZBwrvm+cedCcQy"}],"_useOriginalSize":false,"_string":"幸运榜","_N$string":"幸运榜","_fontSize":22,"_lineHeight":22,"_N$horizontalAlign":1,"_N$verticalAlign":1}],"_contentSize":{"__type__":"cc.Size","width":66,"height":27.72},"_position":{"__type__":"cc.Vec3","x":-33.474}},{"__type__":"cc.Node","_name":"btn_mine","_parent":{"__id__":39},"_children":[{"__id__":45}],"_level":3,"_components":[{"__type__":"cc.Sprite","node":{"__id__":44},"_materials":[{"__uuid__":"ecpdLyjvZBwrvm+cedCcQy"}],"_spriteFrame":{"__uuid__":"56BCNST/1HKZSMhWXV1CKM"}},{"__type__":"cc.Button","node":{"__id__":44}}],"_contentSize":{"__type__":"cc.Size","width":80,"height":57},"_anchorPoint":{"__type__":"cc.Vec2","x":1,"y":0.5},"_position":{"__type__":"cc.Vec3","y":-133}},{"__type__":"cc.Node","_name":"New Label","_parent":{"__id__":44},"_level":4,"_components":[{"__type__":"cc.Label","node":{"__id__":45},"_materials":[{"__uuid__":"ecpdLyjvZBwrvm+cedCcQy"}],"_useOriginalSize":false,"_string":"我的","_N$string":"我的","_fontSize":22,"_lineHeight":22,"_N$horizontalAlign":1,"_N$verticalAlign":1}],"_contentSize":{"__type__":"cc.Size","width":44,"height":27.72},"_position":{"__type__":"cc.Vec3","x":-33.474}},{"__type__":"cc.Node","_name":"nod_rule","_parent":{"__id__":7},"_children":[{"__id__":47},{"__id__":48},{"__id__":49},{"__id__":50}],"_active":false,"_level":2,"_position":{"__type__":"cc.Vec3","y":-652.761},"groupIndex":1},{"__type__":"cc.Node","_name":"mask","_parent":{"__id__":46},"_level":3,"_components":[{"__type__":"cc.BlockInputEvents","node":{"__id__":47}},{"__type__":"cc.Sprite","node":{"__id__":47},"_materials":[{"__uuid__":"ecpdLyjvZBwrvm+cedCcQy"}],"_spriteFrame":{"__uuid__":"9bvaMerUlDyary99mJa6xp"},"_sizeMode":0}],"_opacity":101,"_color":{"__type__":"cc.Color"},"_contentSize":{"__type__":"cc.Size","width":2000,"height":2000}},{"__type__":"cc.Node","_name":"New Sprite","_parent":{"__id__":46},"_level":3,"_components":[{"__type__":"cc.Sprite","node":{"__id__":48},"_materials":[{"__uuid__":"ecpdLyjvZBwrvm+cedCcQy"}],"_spriteFrame":{"__uuid__":"32fgqcUOlFObUiXSzcOYJD"}}],"_contentSize":{"__type__":"cc.Size","width":620,"height":808}},{"__type__":"cc.Node","_name":"btn_confirm","_parent":{"__id__":46},"_level":3,"_components":[{"__type__":"cc.Sprite","node":{"__id__":49},"_materials":[{"__uuid__":"ecpdLyjvZBwrvm+cedCcQy"}],"_spriteFrame":{"__uuid__":"9afd9CBEtPD5wTE9lsphfG"}},{"__type__":"cc.Button","node":{"__id__":49},"clickEvents":[{"__type__":"cc.ClickEvent","target":{"__id__":2},"_componentId":"658dcTqCq1EsYsnCLnPmDep","handler":"onRuleConfirm"}]}],"_contentSize":{"__type__":"cc.Size","width":190,"height":75},"_position":{"__type__":"cc.Vec3","y":-329.374}},{"__type__":"cc.Node","_name":"New Label","_parent":{"__id__":46},"_level":3,"_components":[{"__type__":"cc.Label","node":{"__id__":50},"_materials":[{"__uuid__":"ecpdLyjvZBwrvm+cedCcQy"}],"_useOriginalSize":false,"_string":"1.盲盒规则：用户花费20000椰豆后氪选择任意一个盲盒开启，花费38000椰豆可同时开启两个盲盒，花费54000椰豆后可同时开启三个盲盒。打开盲盒即可获得惊喜奖品，购买盲盒可100%开出奖品，奖品价值9.9元到7999元不等。\n\n2.盲盒规则：用户花费20000椰豆后氪选择任意一个盲盒开启，花费38000椰豆可同时开启两个盲盒，花费54000椰豆后可同时开启三个盲盒。打开盲盒即可获得惊喜奖品，购买盲盒可100%开出奖品，奖品价值9.9元到7999元不等。\n\n3.盲盒规则：用户花费20000椰豆后氪选择任意一个盲盒开启，花费38000椰豆可同时开启两个盲盒，花费54000椰豆后可同时开启三个盲盒。打开盲盒即可获得惊喜奖品，购买盲盒可100%开出奖品，奖品价值9.9元到7999元不等。","_N$string":"1.盲盒规则：用户花费20000椰豆后氪选择任意一个盲盒开启，花费38000椰豆可同时开启两个盲盒，花费54000椰豆后可同时开启三个盲盒。打开盲盒即可获得惊喜奖品，购买盲盒可100%开出奖品，奖品价值9.9元到7999元不等。\n\n2.盲盒规则：用户花费20000椰豆后氪选择任意一个盲盒开启，花费38000椰豆可同时开启两个盲盒，花费54000椰豆后可同时开启三个盲盒。打开盲盒即可获得惊喜奖品，购买盲盒可100%开出奖品，奖品价值9.9元到7999元不等。\n\n3.盲盒规则：用户花费20000椰豆后氪选择任意一个盲盒开启，花费38000椰豆可同时开启两个盲盒，花费54000椰豆后可同时开启三个盲盒。打开盲盒即可获得惊喜奖品，购买盲盒可100%开出奖品，奖品价值9.9元到7999元不等。","_fontSize":22,"_lineHeight":36,"_N$verticalAlign":1,"_N$overflow":3}],"_color":{"__type__":"cc.Color","r":83,"g":58,"b":3},"_contentSize":{"__type__":"cc.Size","width":575,"height":513.36},"_position":{"__type__":"cc.Vec3","y":29}},{"__type__":"cc.Node","_name":"nod_more","_parent":{"__id__":7},"_children":[{"__id__":52},{"__id__":53},{"__id__":54},{"__id__":55},{"__id__":56}],"_active":false,"_level":3,"_components":[{"__id__":64}],"_position":{"__type__":"cc.Vec3","y":-652.761},"groupIndex":1},{"__type__":"cc.Node","_name":"mask","_parent":{"__id__":51},"_level":3,"_components":[{"__type__":"cc.BlockInputEvents","node":{"__id__":52}},{"__type__":"cc.Sprite","node":{"__id__":52},"_materials":[{"__uuid__":"ecpdLyjvZBwrvm+cedCcQy"}],"_spriteFrame":{"__uuid__":"9bvaMerUlDyary99mJa6xp"},"_sizeMode":0}],"_opacity":101,"_color":{"__type__":"cc.Color"},"_contentSize":{"__type__":"cc.Size","width":2000,"height":2000}},{"__type__":"cc.Node","_name":"New Sprite","_parent":{"__id__":51},"_level":3,"_components":[{"__type__":"cc.Sprite","node":{"__id__":53},"_materials":[{"__uuid__":"ecpdLyjvZBwrvm+cedCcQy"}],"_spriteFrame":{"__uuid__":"61vnkMzDJB77BPIy4f27EF"}}],"_contentSize":{"__type__":"cc.Size","width":686,"height":984}},{"__type__":"cc.Node","_name":"btn_close","_parent":{"__id__":51},"_level":3,"_components":[{"__type__":"cc.Sprite","node":{"__id__":54},"_materials":[{"__uuid__":"ecpdLyjvZBwrvm+cedCcQy"}],"_spriteFrame":{"__uuid__":"bfXhp7jllOwYVqrsn8TCkZ"}},{"__type__":"cc.Button","node":{"__id__":54},"clickEvents":[{"__type__":"cc.ClickEvent","target":{"__id__":51},"_componentId":"ed44fRCaAJGPZu92qYY7TRs","handler":"onBtnClose"}]}],"_opacity":100,"_color":{"__type__":"cc.Color"},"_contentSize":{"__type__":"cc.Size","width":34,"height":34},"_position":{"__type__":"cc.Vec3","x":285.321,"y":446.464}},{"__type__":"cc.Node","_name":"New Label","_parent":{"__id__":51},"_level":4,"_components":[{"__type__":"cc.Label","node":{"__id__":55},"_materials":[{"__uuid__":"ecpdLyjvZBwrvm+cedCcQy"}],"_useOriginalSize":false,"_string":"所有商品","_N$string":"所有商品","_N$horizontalAlign":1,"_N$verticalAlign":1}],"_color":{"__type__":"cc.Color"},"_contentSize":{"__type__":"cc.Size","width":160,"height":50.4},"_position":{"__type__":"cc.Vec3","y":423.238}},{"__type__":"cc.Node","_name":"New ScrollView","_parent":{"__id__":51},"_children":[{"__id__":57},{"__id__":63}],"_level":4,"_components":[{"__type__":"cc.Sprite","node":{"__id__":56},"_enabled":false,"_materials":[{"__uuid__":"ecpdLyjvZBwrvm+cedCcQy"}],"_spriteFrame":{"__uuid__":"9bvaMerUlDyary99mJa6xp"},"_type":1,"_sizeMode":0},{"__id__":61}],"_contentSize":{"__type__":"cc.Size","width":680,"height":850},"_anchorPoint":{"__type__":"cc.Vec2","x":0.5,"y":1},"_position":{"__type__":"cc.Vec3","y":359.263}},{"__type__":"cc.Node","_name":"scrollBar","_parent":{"__id__":56},"_children":[{"__id__":58}],"_active":false,"_components":[{"__id__":60},{"__type__":"cc.Widget","node":{"__id__":57},"alignMode":0,"_alignFlags":37,"_left":350.07654921020657,"_originalHeight":237},{"__type__":"cc.Sprite","node":{"__id__":57},"_materials":[{"__uuid__":"ecpdLyjvZBwrvm+cedCcQy"}],"_spriteFrame":{"__uuid__":"5f5dyqtRNNxaFmVzYns6FZ"},"_type":1,"_sizeMode":0}],"_opacity":0,"_contentSize":{"__type__":"cc.Size","width":12,"height":850},"_anchorPoint":{"__type__":"cc.Vec2","x":1,"y":0.5},"_position":{"__type__":"cc.Vec3","x":340,"y":-425}},{"__type__":"cc.Node","_name":"bar","_parent":{"__id__":57},"_components":[{"__id__":59}],"_opacity":0,"_contentSize":{"__type__":"cc.Size","width":10,"height":30},"_anchorPoint":{"__type__":"cc.Vec2","x":1},"_position":{"__type__":"cc.Vec3","x":-1}},{"__type__":"cc.Sprite","node":{"__id__":58},"_materials":[{"__uuid__":"ecpdLyjvZBwrvm+cedCcQy"}],"_spriteFrame":{"__uuid__":"5cO7kybDxGj4ipyMYdRYZB"},"_type":1,"_sizeMode":0},{"__type__":"cc.Scrollbar","node":{"__id__":57},"_scrollView":{"__id__":61},"_N$handle":{"__id__":59},"_N$direction":1},{"__type__":"cc.ScrollView","node":{"__id__":56},"horizontal":false,"brake":0.75,"bounceDuration":0.23,"_N$content":{"__id__":62},"content":{"__id__":62},"_N$horizontalScrollBar":null,"_N$verticalScrollBar":{"__id__":60}},{"__type__":"cc.Node","_name":"content","_parent":{"__id__":63},"_level":1,"_components":[{"__type__":"cc.Layout","node":{"__id__":62},"_layoutSize":{"__type__":"cc.Size","width":684,"height":200},"_resize":1,"_N$layoutType":3,"_N$paddingLeft":35,"_N$paddingTop":7,"_N$spacingX":20,"_N$spacingY":20}],"_contentSize":{"__type__":"cc.Size","width":684,"height":200},"_anchorPoint":{"__type__":"cc.Vec2","x":0.5,"y":1}},{"__type__":"cc.Node","_name":"view","_parent":{"__id__":56},"_children":[{"__id__":62}],"_components":[{"__type__":"cc.Mask","node":{"__id__":63},"_materials":[{"__uuid__":"ecpdLyjvZBwrvm+cedCcQy"}]}],"_contentSize":{"__type__":"cc.Size","width":680,"height":850},"_anchorPoint":{"__type__":"cc.Vec2","x":0.5,"y":1}},{"__type__":"ed44fRCaAJGPZu92qYY7TRs","node":{"__id__":51},"content":{"__id__":62},"propItem":{"__uuid__":"41lezCW3ZD0Z/j3PDfCB20"}},{"__type__":"cc.Node","_name":"nod_rank","_parent":{"__id__":7},"_children":[{"__id__":66},{"__id__":67},{"__id__":68},{"__id__":69},{"__id__":70}],"_active":false,"_level":3,"_components":[{"__type__":"87ee1shWf9FOZD63oK9w+e9","node":{"__id__":65},"content":{"__id__":76},"rankItem":{"__uuid__":"3cVMEdZQ9E1IaRlhduId9Q"}}],"_position":{"__type__":"cc.Vec3","y":-652.761},"groupIndex":1},{"__type__":"cc.Node","_name":"mask","_parent":{"__id__":65},"_level":3,"_components":[{"__type__":"cc.BlockInputEvents","node":{"__id__":66}},{"__type__":"cc.Sprite","node":{"__id__":66},"_materials":[{"__uuid__":"ecpdLyjvZBwrvm+cedCcQy"}],"_spriteFrame":{"__uuid__":"9bvaMerUlDyary99mJa6xp"},"_sizeMode":0}],"_opacity":101,"_color":{"__type__":"cc.Color"},"_contentSize":{"__type__":"cc.Size","width":2000,"height":2000}},{"__type__":"cc.Node","_name":"New Sprite","_parent":{"__id__":65},"_level":3,"_components":[{"__type__":"cc.Sprite","node":{"__id__":67},"_materials":[{"__uuid__":"ecpdLyjvZBwrvm+cedCcQy"}],"_spriteFrame":{"__uuid__":"61vnkMzDJB77BPIy4f27EF"}}],"_contentSize":{"__type__":"cc.Size","width":686,"height":984}},{"__type__":"cc.Node","_name":"btn_close","_parent":{"__id__":65},"_level":3,"_components":[{"__type__":"cc.Sprite","node":{"__id__":68},"_materials":[{"__uuid__":"ecpdLyjvZBwrvm+cedCcQy"}],"_spriteFrame":{"__uuid__":"bfXhp7jllOwYVqrsn8TCkZ"}},{"__type__":"cc.Button","node":{"__id__":68},"clickEvents":[{"__type__":"cc.ClickEvent","target":{"__id__":65},"_componentId":"87ee1shWf9FOZD63oK9w+e9","handler":"onBtnClose"}]}],"_opacity":100,"_color":{"__type__":"cc.Color"},"_contentSize":{"__type__":"cc.Size","width":34,"height":34},"_position":{"__type__":"cc.Vec3","x":285.321,"y":446.464}},{"__type__":"cc.Node","_name":"New Label","_parent":{"__id__":65},"_level":4,"_components":[{"__type__":"cc.Label","node":{"__id__":69},"_materials":[{"__uuid__":"ecpdLyjvZBwrvm+cedCcQy"}],"_useOriginalSize":false,"_string":"幸运榜","_N$string":"幸运榜","_N$horizontalAlign":1,"_N$verticalAlign":1}],"_color":{"__type__":"cc.Color"},"_contentSize":{"__type__":"cc.Size","width":120,"height":50.4},"_position":{"__type__":"cc.Vec3","y":423.238}},{"__type__":"cc.Node","_name":"New ScrollView","_parent":{"__id__":65},"_children":[{"__id__":71},{"__id__":77}],"_level":4,"_components":[{"__type__":"cc.Sprite","node":{"__id__":70},"_enabled":false,"_materials":[{"__uuid__":"ecpdLyjvZBwrvm+cedCcQy"}],"_spriteFrame":{"__uuid__":"9bvaMerUlDyary99mJa6xp"},"_type":1,"_sizeMode":0},{"__id__":75}],"_contentSize":{"__type__":"cc.Size","width":680,"height":850},"_anchorPoint":{"__type__":"cc.Vec2","x":0.5,"y":1},"_position":{"__type__":"cc.Vec3","y":359.263}},{"__type__":"cc.Node","_name":"scrollBar","_parent":{"__id__":70},"_children":[{"__id__":72}],"_active":false,"_components":[{"__id__":74},{"__type__":"cc.Widget","node":{"__id__":71},"alignMode":0,"_alignFlags":37,"_left":350.07654921020657,"_originalHeight":237},{"__type__":"cc.Sprite","node":{"__id__":71},"_materials":[{"__uuid__":"ecpdLyjvZBwrvm+cedCcQy"}],"_spriteFrame":{"__uuid__":"5f5dyqtRNNxaFmVzYns6FZ"},"_type":1,"_sizeMode":0}],"_opacity":0,"_contentSize":{"__type__":"cc.Size","width":12,"height":850},"_anchorPoint":{"__type__":"cc.Vec2","x":1,"y":0.5},"_position":{"__type__":"cc.Vec3","x":340,"y":-425}},{"__type__":"cc.Node","_name":"bar","_parent":{"__id__":71},"_components":[{"__id__":73}],"_opacity":0,"_contentSize":{"__type__":"cc.Size","width":10,"height":30},"_anchorPoint":{"__type__":"cc.Vec2","x":1},"_position":{"__type__":"cc.Vec3","x":-1}},{"__type__":"cc.Sprite","node":{"__id__":72},"_materials":[{"__uuid__":"ecpdLyjvZBwrvm+cedCcQy"}],"_spriteFrame":{"__uuid__":"5cO7kybDxGj4ipyMYdRYZB"},"_type":1,"_sizeMode":0},{"__type__":"cc.Scrollbar","node":{"__id__":71},"_scrollView":{"__id__":75},"_N$handle":{"__id__":73},"_N$direction":1},{"__type__":"cc.ScrollView","node":{"__id__":70},"horizontal":false,"brake":0.75,"bounceDuration":0.23,"scrollEvents":[{"__type__":"cc.ClickEvent","target":{"__id__":65},"_componentId":"87ee1shWf9FOZD63oK9w+e9","handler":"onRecordScroll"}],"_N$content":{"__id__":76},"content":{"__id__":76},"_N$horizontalScrollBar":null,"_N$verticalScrollBar":{"__id__":74}},{"__type__":"cc.Node","_name":"content","_parent":{"__id__":77},"_level":1,"_components":[{"__type__":"cc.Layout","node":{"__id__":76},"_layoutSize":{"__type__":"cc.Size","width":684,"height":-13},"_resize":1,"_N$layoutType":2,"_N$paddingLeft":35,"_N$paddingTop":7,"_N$spacingX":20,"_N$spacingY":20}],"_contentSize":{"__type__":"cc.Size","width":684,"height":-13},"_anchorPoint":{"__type__":"cc.Vec2","x":0.5,"y":1}},{"__type__":"cc.Node","_name":"view","_parent":{"__id__":70},"_children":[{"__id__":76}],"_components":[{"__type__":"cc.Mask","node":{"__id__":77},"_materials":[{"__uuid__":"ecpdLyjvZBwrvm+cedCcQy"}]}],"_contentSize":{"__type__":"cc.Size","width":680,"height":850},"_anchorPoint":{"__type__":"cc.Vec2","x":0.5,"y":1}},{"__type__":"cc.Node","_name":"nod_open","_parent":{"__id__":7},"_children":[{"__id__":79},{"__id__":80},{"__id__":81},{"__id__":82},{"__id__":83},{"__id__":84}],"_active":false,"_level":3,"_components":[{"__id__":87}],"_position":{"__type__":"cc.Vec3","y":-652.761},"groupIndex":1},{"__type__":"cc.Node","_name":"mask","_parent":{"__id__":78},"_level":3,"_components":[{"__type__":"cc.BlockInputEvents","node":{"__id__":79}},{"__type__":"cc.Sprite","node":{"__id__":79},"_materials":[{"__uuid__":"ecpdLyjvZBwrvm+cedCcQy"}],"_spriteFrame":{"__uuid__":"9bvaMerUlDyary99mJa6xp"},"_sizeMode":0}],"_opacity":150,"_color":{"__type__":"cc.Color"},"_contentSize":{"__type__":"cc.Size","width":2000,"height":2000}},{"__type__":"cc.Node","_name":"spr_bg","_parent":{"__id__":78},"_level":3,"_components":[{"__type__":"cc.Sprite","node":{"__id__":80},"_materials":[{"__uuid__":"ecpdLyjvZBwrvm+cedCcQy"}],"_spriteFrame":{"__uuid__":"92qCtwkvRNqIujZyIxu9Q7"}}],"_contentSize":{"__type__":"cc.Size","width":644,"height":645}},{"__type__":"cc.Node","_name":"New Sprite copy","_parent":{"__id__":78},"_level":4,"_components":[{"__type__":"cc.Sprite","node":{"__id__":81},"_materials":[{"__uuid__":"ecpdLyjvZBwrvm+cedCcQy"}],"_spriteFrame":{"__uuid__":"b0CWWFyUhGMZ8mLg365xGu"}}],"_contentSize":{"__type__":"cc.Size","width":269,"height":331}},{"__type__":"cc.Node","_name":"btn_confirm","_parent":{"__id__":78},"_level":3,"_components":[{"__type__":"cc.Sprite","node":{"__id__":82},"_materials":[{"__uuid__":"ecpdLyjvZBwrvm+cedCcQy"}],"_spriteFrame":{"__uuid__":"63Vyj2V+RB3ou/uXFmTJAC"}},{"__type__":"cc.Button","node":{"__id__":82},"clickEvents":[{"__type__":"cc.ClickEvent","target":{"__id__":78},"_componentId":"f3082YCAlJAFpeaaud+XITF","handler":"onBtnOpen"}]}],"_contentSize":{"__type__":"cc.Size","width":220,"height":72},"_position":{"__type__":"cc.Vec3","y":-329.374}},{"__type__":"cc.Node","_name":"btn_close","_parent":{"__id__":78},"_level":4,"_components":[{"__type__":"cc.Sprite","node":{"__id__":83},"_materials":[{"__uuid__":"ecpdLyjvZBwrvm+cedCcQy"}],"_spriteFrame":{"__uuid__":"bfXhp7jllOwYVqrsn8TCkZ"}},{"__type__":"cc.Button","node":{"__id__":83},"clickEvents":[{"__type__":"cc.ClickEvent","target":{"__id__":78},"_componentId":"f3082YCAlJAFpeaaud+XITF","handler":"onBtnClose"}]}],"_contentSize":{"__type__":"cc.Size","width":34,"height":34},"_position":{"__type__":"cc.Vec3","x":255.628,"y":215.224}},{"__type__":"cc.Node","_name":"btn_check","_parent":{"__id__":78},"_children":[{"__id__":85},{"__id__":86}],"_level":4,"_components":[{"__type__":"cc.Sprite","node":{"__id__":84},"_materials":[{"__uuid__":"ecpdLyjvZBwrvm+cedCcQy"}],"_spriteFrame":{"__uuid__":"83SP3FFv5Jrrs6iBu3NBjq"}},{"__type__":"cc.Button","node":{"__id__":84},"clickEvents":[{"__type__":"cc.ClickEvent","target":{"__id__":78},"_componentId":"f3082YCAlJAFpeaaud+XITF","handler":"onBtnCheck"}]}],"_contentSize":{"__type__":"cc.Size","width":364,"height":64},"_position":{"__type__":"cc.Vec3","y":-237.681}},{"__type__":"cc.Node","_name":"New Sprite","_parent":{"__id__":84},"_level":5,"_components":[{"__type__":"cc.Sprite","node":{"__id__":85},"_materials":[{"__uuid__":"ecpdLyjvZBwrvm+cedCcQy"}],"_spriteFrame":{"__uuid__":"4evdIqB2BK26vS4kI7hITk"}}],"_contentSize":{"__type__":"cc.Size","width":48,"height":37},"_position":{"__type__":"cc.Vec3","x":-91.757}},{"__type__":"cc.Node","_name":"New Label","_parent":{"__id__":84},"_level":5,"_components":[{"__type__":"cc.Label","node":{"__id__":86},"_materials":[{"__uuid__":"ecpdLyjvZBwrvm+cedCcQy"}],"_useOriginalSize":false,"_string":"使用透视卡","_N$string":"使用透视卡","_fontSize":35,"_N$horizontalAlign":1,"_N$verticalAlign":1}],"_contentSize":{"__type__":"cc.Size","width":175,"height":50.4},"_position":{"__type__":"cc.Vec3","x":35.424}},{"__type__":"f3082YCAlJAFpeaaud+XITF","node":{"__id__":78},"bg":{"__id__":80},"check":{"__id__":84},"checkLayer":{"__id__":88},"openedLayer":{"__id__":114}},{"__type__":"bee5bcAV6FLGod3GcP4qYZS","node":{"__id__":89},"richText":{"__id__":99},"checkOpenLayer":{"__id__":100},"nodOpen":{"__id__":87}},{"__type__":"cc.Node","_name":"checkLayer","_parent":{"__id__":7},"_children":[{"__id__":90},{"__id__":91},{"__id__":92},{"__id__":93},{"__id__":94},{"__id__":95}],"_active":false,"_level":3,"_components":[{"__id__":88}],"_position":{"__type__":"cc.Vec3","y":-652.761},"groupIndex":1},{"__type__":"cc.Node","_name":"mask","_parent":{"__id__":89},"_level":3,"_components":[{"__type__":"cc.BlockInputEvents","node":{"__id__":90}},{"__type__":"cc.Sprite","node":{"__id__":90},"_materials":[{"__uuid__":"ecpdLyjvZBwrvm+cedCcQy"}],"_spriteFrame":{"__uuid__":"9bvaMerUlDyary99mJa6xp"},"_sizeMode":0}],"_opacity":150,"_color":{"__type__":"cc.Color"},"_contentSize":{"__type__":"cc.Size","width":2000,"height":2000}},{"__type__":"cc.Node","_name":"spr_bg","_parent":{"__id__":89},"_level":3,"_components":[{"__type__":"cc.Sprite","node":{"__id__":91},"_materials":[{"__uuid__":"ecpdLyjvZBwrvm+cedCcQy"}],"_spriteFrame":{"__uuid__":"d3f0SIdbBIgLZR8QP2bBj7"}}],"_contentSize":{"__type__":"cc.Size","width":620,"height":418}},{"__type__":"cc.Node","_name":"btn_confirm","_parent":{"__id__":89},"_level":3,"_components":[{"__type__":"cc.Sprite","node":{"__id__":92},"_materials":[{"__uuid__":"ecpdLyjvZBwrvm+cedCcQy"}],"_spriteFrame":{"__uuid__":"8bLqJRoI9ObK74TsmlB/JG"}},{"__type__":"cc.Button","node":{"__id__":92},"clickEvents":[{"__type__":"cc.ClickEvent","target":{"__id__":89},"_componentId":"bee5bcAV6FLGod3GcP4qYZS","handler":"onBtnCheck"}]}],"_contentSize":{"__type__":"cc.Size","width":220,"height":72},"_position":{"__type__":"cc.Vec3","x":155.28,"y":-122.333}},{"__type__":"cc.Node","_name":"btn_close","_parent":{"__id__":89},"_level":4,"_components":[{"__type__":"cc.Sprite","node":{"__id__":93},"_materials":[{"__uuid__":"ecpdLyjvZBwrvm+cedCcQy"}],"_spriteFrame":{"__uuid__":"80nQdPOPtGpqQXGtn0vXB5"}},{"__type__":"cc.Button","node":{"__id__":93},"clickEvents":[{"__type__":"cc.ClickEvent","target":{"__id__":89},"_componentId":"bee5bcAV6FLGod3GcP4qYZS","handler":"onBtnClose"}]}],"_contentSize":{"__type__":"cc.Size","width":220,"height":72},"_position":{"__type__":"cc.Vec3","x":-134.926,"y":-123.57}},{"__type__":"cc.Node","_name":"New Label","_parent":{"__id__":89},"_level":4,"_components":[{"__type__":"cc.Label","node":{"__id__":94},"_materials":[{"__uuid__":"ecpdLyjvZBwrvm+cedCcQy"}],"_useOriginalSize":false,"_string":"透视卡能帮您看出宝盒中是否是你心仪的奖品哦","_N$string":"透视卡能帮您看出宝盒中是否是你心仪的奖品哦","_fontSize":25,"_lineHeight":20,"_N$horizontalAlign":1,"_N$verticalAlign":1}],"_color":{"__type__":"cc.Color","r":83,"g":58,"b":3},"_contentSize":{"__type__":"cc.Size","width":525,"height":25.2},"_position":{"__type__":"cc.Vec3","y":1}},{"__type__":"cc.Node","_name":"New RichText","_parent":{"__id__":89},"_children":[{"__id__":96},{"__id__":97},{"__id__":98}],"_level":4,"_components":[{"__id__":99}],"_contentSize":{"__type__":"cc.Size","width":456.74,"height":63},"_position":{"__type__":"cc.Vec3","y":57}},{"__type__":"cc.PrivateNode","_name":"RICHTEXT_CHILD","_objFlags":1024,"_parent":{"__id__":95},"_active":false,"_level":5,"_components":[{"__type__":"cc.Label","node":{"__id__":96},"_materials":[{"__uuid__":"ecpdLyjvZBwrvm+cedCcQy"}],"_string":"您是否使用","_N$string":"您是否使用","_fontSize":30,"_lineHeight":50,"_N$verticalAlign":1}],"_color":{"__type__":"cc.Color","r":83,"g":58,"b":3},"_contentSize":{"__type__":"cc.Size","width":150,"height":63},"_anchorPoint":{"__type__":"cc.Vec2"},"_position":{"__type__":"cc.Vec3","x":-228.37,"y":-31.5}},{"__type__":"cc.PrivateNode","_name":"RICHTEXT_CHILD","_objFlags":1024,"_parent":{"__id__":95},"_active":false,"_level":5,"_components":[{"__type__":"cc.Label","node":{"__id__":97},"_materials":[{"__uuid__":"ecpdLyjvZBwrvm+cedCcQy"}],"_string":"5000呗豆","_N$string":"5000呗豆","_fontSize":30,"_lineHeight":50,"_N$verticalAlign":1}],"_color":{"__type__":"cc.Color","r":230,"g":74,"b":70},"_contentSize":{"__type__":"cc.Size","width":126.74,"height":63},"_anchorPoint":{"__type__":"cc.Vec2"},"_position":{"__type__":"cc.Vec3","x":-78.37,"y":-31.5}},{"__type__":"cc.PrivateNode","_name":"RICHTEXT_CHILD","_objFlags":1024,"_parent":{"__id__":95},"_active":false,"_level":5,"_components":[{"__type__":"cc.Label","node":{"__id__":98},"_materials":[{"__uuid__":"ecpdLyjvZBwrvm+cedCcQy"}],"_string":"，透视该宝盒","_N$string":"，透视该宝盒","_fontSize":30,"_lineHeight":50,"_N$verticalAlign":1}],"_color":{"__type__":"cc.Color","r":83,"g":58,"b":3},"_contentSize":{"__type__":"cc.Size","width":180,"height":63},"_anchorPoint":{"__type__":"cc.Vec2"},"_position":{"__type__":"cc.Vec3","x":48.370000000000005,"y":-31.5}},{"__type__":"cc.RichText","node":{"__id__":95},"_N$string":"<color=#533A03>您是否使用</c><color=#e64a46>5000呗豆</color><color=#533A03>，透视该宝盒</c>","_N$fontSize":30,"_N$lineHeight":50},{"__type__":"0c082PeFQNPvYh5OTGXCAVT","node":{"__id__":101},"bg":{"__id__":103},"boxValue":{"__id__":113},"spr_goods":{"__id__":106},"openedLayer":{"__id__":114}},{"__type__":"cc.Node","_name":"checkOpenLayer","_parent":{"__id__":7},"_children":[{"__id__":102},{"__id__":103},{"__id__":104},{"__id__":105},{"__id__":107},{"__id__":108},{"__id__":109}],"_active":false,"_level":3,"_components":[{"__id__":100}],"_position":{"__type__":"cc.Vec3","y":-652.761},"groupIndex":1},{"__type__":"cc.Node","_name":"mask","_parent":{"__id__":101},"_level":3,"_components":[{"__type__":"cc.BlockInputEvents","node":{"__id__":102}},{"__type__":"cc.Sprite","node":{"__id__":102},"_materials":[{"__uuid__":"ecpdLyjvZBwrvm+cedCcQy"}],"_spriteFrame":{"__uuid__":"9bvaMerUlDyary99mJa6xp"},"_sizeMode":0}],"_opacity":150,"_color":{"__type__":"cc.Color"},"_contentSize":{"__type__":"cc.Size","width":2000,"height":2000}},{"__type__":"cc.Node","_name":"spr_bg","_parent":{"__id__":101},"_level":3,"_components":[{"__type__":"cc.Sprite","node":{"__id__":103},"_materials":[{"__uuid__":"ecpdLyjvZBwrvm+cedCcQy"}],"_spriteFrame":{"__uuid__":"92qCtwkvRNqIujZyIxu9Q7"}}],"_contentSize":{"__type__":"cc.Size","width":644,"height":645}},{"__type__":"cc.Node","_name":"New Sprite copy","_parent":{"__id__":101},"_level":4,"_components":[{"__type__":"cc.Sprite","node":{"__id__":104},"_materials":[{"__uuid__":"ecpdLyjvZBwrvm+cedCcQy"}],"_spriteFrame":{"__uuid__":"b0CWWFyUhGMZ8mLg365xGu"}}],"_contentSize":{"__type__":"cc.Size","width":269,"height":331}},{"__type__":"cc.Node","_name":"spr_goods","_parent":{"__id__":101},"_level":4,"_components":[{"__id__":106}],"_opacity":200,"_contentSize":{"__type__":"cc.Size","width":200,"height":200},"_position":{"__type__":"cc.Vec3","y":-47.055}},{"__type__":"cc.Sprite","node":{"__id__":105},"_materials":[{"__uuid__":"ecpdLyjvZBwrvm+cedCcQy"}],"_spriteFrame":{"__uuid__":"8c20Sso/ZEn7NUfNSM+EBh"},"_sizeMode":0},{"__type__":"cc.Node","_name":"btn_confirm","_parent":{"__id__":101},"_level":3,"_components":[{"__type__":"cc.Sprite","node":{"__id__":107},"_materials":[{"__uuid__":"ecpdLyjvZBwrvm+cedCcQy"}],"_spriteFrame":{"__uuid__":"48Mqz2CbhJYKyU+ly2Ut2m"}},{"__type__":"cc.Button","node":{"__id__":107},"clickEvents":[{"__type__":"cc.ClickEvent","target":{"__id__":101},"_componentId":"0c082PeFQNPvYh5OTGXCAVT","handler":"onBtnOpen"}]}],"_contentSize":{"__type__":"cc.Size","width":220,"height":72},"_position":{"__type__":"cc.Vec3","y":-329.374}},{"__type__":"cc.Node","_name":"btn_close","_parent":{"__id__":101},"_level":4,"_components":[{"__type__":"cc.Sprite","node":{"__id__":108},"_materials":[{"__uuid__":"ecpdLyjvZBwrvm+cedCcQy"}],"_spriteFrame":{"__uuid__":"bfXhp7jllOwYVqrsn8TCkZ"}},{"__type__":"cc.Button","node":{"__id__":108},"clickEvents":[{"__type__":"cc.ClickEvent","target":{"__id__":101},"_componentId":"0c082PeFQNPvYh5OTGXCAVT","handler":"onBtnClose"}]}],"_contentSize":{"__type__":"cc.Size","width":34,"height":34},"_position":{"__type__":"cc.Vec3","x":255.628,"y":215.224}},{"__type__":"cc.Node","_name":"New Node","_parent":{"__id__":101},"_children":[{"__id__":110},{"__id__":111},{"__id__":112}],"_level":4,"_components":[{"__type__":"cc.Layout","node":{"__id__":109},"_layoutSize":{"__type__":"cc.Size","width":214.1,"height":50.4},"_resize":1,"_N$layoutType":1,"_N$spacingX":4}],"_contentSize":{"__type__":"cc.Size","width":214.1,"height":50.4},"_position":{"__type__":"cc.Vec3","y":-239.447}},{"__type__":"cc.Node","_name":"New Label","_parent":{"__id__":109},"_level":5,"_components":[{"__type__":"cc.Label","node":{"__id__":110},"_materials":[{"__uuid__":"ecpdLyjvZBwrvm+cedCcQy"}],"_useOriginalSize":false,"_string":"价值","_N$string":"价值","_N$horizontalAlign":1,"_N$verticalAlign":1}],"_color":{"__type__":"cc.Color","r":223,"g":114,"b":32},"_contentSize":{"__type__":"cc.Size","width":80,"height":50.4},"_position":{"__type__":"cc.Vec3","x":-67.05}},{"__type__":"cc.Node","_name":"New Sprite","_parent":{"__id__":109},"_level":5,"_components":[{"__type__":"cc.Sprite","node":{"__id__":111},"_materials":[{"__uuid__":"ecpdLyjvZBwrvm+cedCcQy"}],"_spriteFrame":{"__uuid__":"73e5Bxt3NI7bewZbEaeEj7"}}],"_contentSize":{"__type__":"cc.Size","width":26,"height":28},"_position":{"__type__":"cc.Vec3","x":-10.049999999999997}},{"__type__":"cc.Node","_name":"lbl_value","_parent":{"__id__":109},"_level":5,"_components":[{"__id__":113}],"_color":{"__type__":"cc.Color","r":223,"g":114,"b":32},"_contentSize":{"__type__":"cc.Size","width":100.1,"height":50.4},"_position":{"__type__":"cc.Vec3","x":57}},{"__type__":"cc.Label","node":{"__id__":112},"_materials":[{"__uuid__":"ecpdLyjvZBwrvm+cedCcQy"}],"_useOriginalSize":false,"_string":"489.0","_N$string":"489.0","_N$horizontalAlign":1,"_N$verticalAlign":1},{"__type__":"a41b8Rx57BDqZ3r+uQvmWqs","node":{"__id__":115},"bg":{"__id__":117},"item":{"__id__":129}},{"__type__":"cc.Node","_name":"openedLayer","_parent":{"__id__":7},"_children":[{"__id__":116},{"__id__":117},{"__id__":118},{"__id__":119}],"_active":false,"_level":3,"_components":[{"__id__":114}],"_position":{"__type__":"cc.Vec3","y":-652.761},"groupIndex":1},{"__type__":"cc.Node","_name":"mask","_parent":{"__id__":115},"_level":3,"_components":[{"__type__":"cc.BlockInputEvents","node":{"__id__":116}},{"__type__":"cc.Sprite","node":{"__id__":116},"_materials":[{"__uuid__":"ecpdLyjvZBwrvm+cedCcQy"}],"_spriteFrame":{"__uuid__":"9bvaMerUlDyary99mJa6xp"},"_sizeMode":0}],"_opacity":150,"_color":{"__type__":"cc.Color"},"_contentSize":{"__type__":"cc.Size","width":2000,"height":2000}},{"__type__":"cc.Node","_name":"spr_bg","_parent":{"__id__":115},"_level":3,"_components":[{"__type__":"cc.Sprite","node":{"__id__":117},"_materials":[{"__uuid__":"ecpdLyjvZBwrvm+cedCcQy"}],"_spriteFrame":{"__uuid__":"92qCtwkvRNqIujZyIxu9Q7"}}],"_contentSize":{"__type__":"cc.Size","width":644,"height":645}},{"__type__":"cc.Node","_name":"btn_close","_parent":{"__id__":115},"_level":4,"_components":[{"__type__":"cc.Sprite","node":{"__id__":118},"_materials":[{"__uuid__":"ecpdLyjvZBwrvm+cedCcQy"}],"_spriteFrame":{"__uuid__":"bfXhp7jllOwYVqrsn8TCkZ"}},{"__type__":"cc.Button","node":{"__id__":118},"clickEvents":[{"__type__":"cc.ClickEvent","target":{"__id__":115},"_componentId":"a41b8Rx57BDqZ3r+uQvmWqs","handler":"onBtnClose"}]}],"_contentSize":{"__type__":"cc.Size","width":34,"height":34},"_position":{"__type__":"cc.Vec3","x":255.628,"y":215.224}},{"__type__":"cc.Node","_name":"item","_parent":{"__id__":115},"_children":[{"__id__":120},{"__id__":122},{"__id__":124}],"_level":4,"_components":[{"__type__":"cc.Sprite","node":{"__id__":119},"_materials":[{"__uuid__":"ecpdLyjvZBwrvm+cedCcQy"}],"_spriteFrame":{"__uuid__":"d4qlqyMh5I/40yJextnuQA"}},{"__id__":129}],"_contentSize":{"__type__":"cc.Size","width":200,"height":272}},{"__type__":"cc.Node","_name":"spr_goods","_parent":{"__id__":119},"_level":5,"_components":[{"__id__":121}],"_opacity":200,"_contentSize":{"__type__":"cc.Size","width":150,"height":150},"_position":{"__type__":"cc.Vec3","y":39.563}},{"__type__":"cc.Sprite","node":{"__id__":120},"_materials":[{"__uuid__":"ecpdLyjvZBwrvm+cedCcQy"}],"_spriteFrame":{"__uuid__":"8c20Sso/ZEn7NUfNSM+EBh"},"_sizeMode":0},{"__type__":"cc.Node","_name":"lbl_name","_parent":{"__id__":119},"_level":5,"_components":[{"__id__":123}],"_color":{"__type__":"cc.Color","r":223,"g":114,"b":32},"_contentSize":{"__type__":"cc.Size","width":80,"height":25.2},"_position":{"__type__":"cc.Vec3","y":-55.893}},{"__type__":"cc.Label","node":{"__id__":122},"_materials":[{"__uuid__":"ecpdLyjvZBwrvm+cedCcQy"}],"_useOriginalSize":false,"_string":"数码相机","_N$string":"数码相机","_fontSize":20,"_lineHeight":20,"_N$horizontalAlign":1,"_N$verticalAlign":1},{"__type__":"cc.Node","_name":"New Node","_parent":{"__id__":119},"_children":[{"__id__":125},{"__id__":126},{"__id__":127}],"_level":5,"_components":[{"__type__":"cc.Layout","node":{"__id__":124},"_layoutSize":{"__type__":"cc.Size","width":124.05,"height":50.4},"_resize":1,"_N$layoutType":1,"_N$spacingX":4}],"_contentSize":{"__type__":"cc.Size","width":124.05,"height":50.4},"_position":{"__type__":"cc.Vec3","y":-92.174}},{"__type__":"cc.Node","_name":"New Label","_parent":{"__id__":124},"_level":5,"_components":[{"__type__":"cc.Label","node":{"__id__":125},"_materials":[{"__uuid__":"ecpdLyjvZBwrvm+cedCcQy"}],"_useOriginalSize":false,"_string":"价值","_N$string":"价值","_fontSize":20,"_lineHeight":20,"_N$horizontalAlign":1,"_N$verticalAlign":1}],"_color":{"__type__":"cc.Color","r":223,"g":114,"b":32},"_contentSize":{"__type__":"cc.Size","width":40,"height":25.2},"_position":{"__type__":"cc.Vec3","x":-42.025000000000006}},{"__type__":"cc.Node","_name":"New Sprite","_parent":{"__id__":124},"_level":5,"_components":[{"__type__":"cc.Sprite","node":{"__id__":126},"_materials":[{"__uuid__":"ecpdLyjvZBwrvm+cedCcQy"}],"_spriteFrame":{"__uuid__":"73e5Bxt3NI7bewZbEaeEj7"}}],"_contentSize":{"__type__":"cc.Size","width":26,"height":28},"_position":{"__type__":"cc.Vec3","x":-5.025000000000006}},{"__type__":"cc.Node","_name":"lbl_value","_parent":{"__id__":124},"_level":5,"_components":[{"__id__":128}],"_color":{"__type__":"cc.Color","r":223,"g":114,"b":32},"_contentSize":{"__type__":"cc.Size","width":50.05,"height":25.2},"_position":{"__type__":"cc.Vec3","x":36.99999999999999}},{"__type__":"cc.Label","node":{"__id__":127},"_materials":[{"__uuid__":"ecpdLyjvZBwrvm+cedCcQy"}],"_useOriginalSize":false,"_string":"489.0","_N$string":"489.0","_fontSize":20,"_lineHeight":20,"_N$horizontalAlign":1,"_N$verticalAlign":1},{"__type__":"ce694EBkw5JGIrJHF+HidtW","node":{"__id__":119},"boxValue":{"__id__":128},"propName":{"__id__":123},"propPic":{"__id__":121}}],{"__type__":"cc.SpriteFrame","content":{"name":"hone_game_bot_bg@2x","texture":"f2BI1clJdCPINNGmY/FTWE","rect":[0,0,304,44],"offset":[0,0],"originalSize":[304,44],"capInsets":[0,0,0,0]}},{"__type__":"cc.SpriteFrame","content":{"name":"popup_bg_ash_long","texture":"22QhE0ZdBJCZRuyHcTEq3f","rect":[0,0,638,160],"offset":[0,0],"originalSize":[638,160],"capInsets":[34,25,29,36]}},{"__type__":"cc.SpriteFrame","content":{"name":"home_game_block_one@2x","texture":"f9UwCbezVO/qbmB5F2it73","rect":[0,0,134,134],"offset":[0,0],"originalSize":[134,134],"capInsets":[0,0,0,0]}},{"__type__":"cc.SpriteFrame","content":{"name":"default_btn_disabled","texture":"71VhFCTINJM6/Ky3oX9nBT","rect":[0,0,40,40],"offset":[0,0],"originalSize":[40,40],"capInsets":[12,12,12,12]}},{"__type__":"cc.SpriteFrame","content":{"name":"home_popup@2x","texture":"ddS3HySCRIMoEr8Q4pKM8x","rect":[0,0,620,808],"offset":[0,0],"originalSize":[620,808],"capInsets":[0,0,0,0]}},[{"__type__":"cc.Prefab","_name":"RankItem","data":{"__id__":1}},{"__type__":"cc.Node","_name":"RankItem","_children":[{"__id__":2},{"__id__":4},{"__id__":6},{"__id__":8},{"__id__":9},{"__id__":11}],"_level":1,"_components":[{"__type__":"cc.Sprite","node":{"__id__":1},"_materials":[{"__uuid__":"ecpdLyjvZBwrvm+cedCcQy"}],"_spriteFrame":{"__uuid__":"133E5QlVFDk4cMTKok5VQS"}},{"__type__":"e24bbvGl/9JBa1OvsU1LIs2","node":{"__id__":1},"boxValue":{"__id__":10},"propName":{"__id__":7},"propPic":{"__id__":12},"userName":{"__id__":5},"sprAvatar":{"__id__":3}}],"_prefab":{"__type__":"cc.PrefabInfo","root":{"__id__":1},"asset":{"__uuid__":"3cVMEdZQ9E1IaRlhduId9Q"},"fileId":"e5rPEyr7NK/bBOg6Ox4/SP"},"_contentSize":{"__type__":"cc.Size","width":638,"height":160}},{"__type__":"cc.Node","_name":"spr_avatar","_parent":{"__id__":1},"_level":3,"_components":[{"__id__":3}],"_prefab":{"__type__":"cc.PrefabInfo","root":{"__id__":1},"asset":{"__uuid__":"3cVMEdZQ9E1IaRlhduId9Q"},"fileId":"efHFCQKg1K76txcdyZBM4x"},"_contentSize":{"__type__":"cc.Size","width":96,"height":96},"_position":{"__type__":"cc.Vec3","x":-254.011}},{"__type__":"cc.Sprite","node":{"__id__":2},"_materials":[{"__uuid__":"ecpdLyjvZBwrvm+cedCcQy"}],"_spriteFrame":{"__uuid__":"d6Gbi/GPRKuYQ17YQzQPEA"},"_sizeMode":0},{"__type__":"cc.Node","_name":"lbl_username","_parent":{"__id__":1},"_level":3,"_components":[{"__id__":5}],"_prefab":{"__type__":"cc.PrefabInfo","root":{"__id__":1},"asset":{"__uuid__":"3cVMEdZQ9E1IaRlhduId9Q"},"fileId":"58n401PANAhZ39d5rnIKz6"},"_color":{"__type__":"cc.Color"},"_contentSize":{"__type__":"cc.Size","width":161.49,"height":31.5},"_anchorPoint":{"__type__":"cc.Vec2","y":0.5},"_position":{"__type__":"cc.Vec3","x":-186,"y":36}},{"__type__":"cc.Label","node":{"__id__":4},"_materials":[{"__uuid__":"ecpdLyjvZBwrvm+cedCcQy"}],"_useOriginalSize":false,"_string":"139******165464","_N$string":"139******165464","_fontSize":22,"_lineHeight":25,"_N$horizontalAlign":1,"_N$verticalAlign":1},{"__type__":"cc.Node","_name":"lbl_name","_parent":{"__id__":1},"_level":3,"_components":[{"__id__":7}],"_prefab":{"__type__":"cc.PrefabInfo","root":{"__id__":1},"asset":{"__uuid__":"3cVMEdZQ9E1IaRlhduId9Q"},"fileId":"411r1AcKxNZINHEqe8iiz/"},"_color":{"__type__":"cc.Color"},"_contentSize":{"__type__":"cc.Size","width":132,"height":31.5},"_anchorPoint":{"__type__":"cc.Vec2","y":0.5},"_position":{"__type__":"cc.Vec3","x":-186,"y":-35}},{"__type__":"cc.Label","node":{"__id__":6},"_materials":[{"__uuid__":"ecpdLyjvZBwrvm+cedCcQy"}],"_useOriginalSize":false,"_string":"康宁空气炸锅","_N$string":"康宁空气炸锅","_fontSize":22,"_lineHeight":25,"_N$horizontalAlign":1,"_N$verticalAlign":1},{"__type__":"cc.Node","_name":"New Sprite","_parent":{"__id__":1},"_level":3,"_components":[{"__type__":"cc.Sprite","node":{"__id__":8},"_materials":[{"__uuid__":"ecpdLyjvZBwrvm+cedCcQy"}],"_spriteFrame":{"__uuid__":"73e5Bxt3NI7bewZbEaeEj7"}}],"_prefab":{"__type__":"cc.PrefabInfo","root":{"__id__":1},"asset":{"__uuid__":"3cVMEdZQ9E1IaRlhduId9Q"},"fileId":"1cv2SuHJ5IsaQ/COZCuuhb"},"_contentSize":{"__type__":"cc.Size","width":26,"height":28},"_position":{"__type__":"cc.Vec3","x":62}},{"__type__":"cc.Node","_name":"lab_value","_parent":{"__id__":1},"_level":3,"_components":[{"__id__":10}],"_prefab":{"__type__":"cc.PrefabInfo","root":{"__id__":1},"asset":{"__uuid__":"3cVMEdZQ9E1IaRlhduId9Q"},"fileId":"75Fth+zF9OrqVH5F1pgppG"},"_color":{"__type__":"cc.Color","r":223,"g":114,"b":32},"_contentSize":{"__type__":"cc.Size","width":62.56,"height":31.5},"_anchorPoint":{"__type__":"cc.Vec2","y":0.5},"_position":{"__type__":"cc.Vec3","x":81}},{"__type__":"cc.Label","node":{"__id__":9},"_materials":[{"__uuid__":"ecpdLyjvZBwrvm+cedCcQy"}],"_useOriginalSize":false,"_string":"489.0","_N$string":"489.0","_fontSize":25,"_lineHeight":25,"_N$horizontalAlign":1,"_N$verticalAlign":1},{"__type__":"cc.Node","_name":"spr_prop","_parent":{"__id__":1},"_level":3,"_components":[{"__id__":12}],"_prefab":{"__type__":"cc.PrefabInfo","root":{"__id__":1},"asset":{"__uuid__":"3cVMEdZQ9E1IaRlhduId9Q"},"fileId":"74BLebp+VAF7VE8W8S6f6N"},"_contentSize":{"__type__":"cc.Size","width":120,"height":120},"_position":{"__type__":"cc.Vec3","x":247}},{"__type__":"cc.Sprite","node":{"__id__":11},"_materials":[{"__uuid__":"ecpdLyjvZBwrvm+cedCcQy"}],"_spriteFrame":{"__uuid__":"8c20Sso/ZEn7NUfNSM+EBh"},"_sizeMode":0}],[{"__type__":"cc.Prefab","_name":"PropItem","data":{"__id__":1}},{"__type__":"cc.Node","_name":"PropItem","_children":[{"__id__":2},{"__id__":4},{"__id__":5},{"__id__":7},{"__id__":9}],"_level":1,"_components":[{"__type__":"cc.Sprite","node":{"__id__":1},"_materials":[{"__uuid__":"ecpdLyjvZBwrvm+cedCcQy"}],"_spriteFrame":{"__uuid__":"133E5QlVFDk4cMTKok5VQS"},"_type":1,"_sizeMode":0},{"__type__":"c3937e+u6JJUqoAo3M+VN3V","node":{"__id__":1},"boxValue":{"__id__":6},"propName":{"__id__":10},"propPic":{"__id__":3},"warehouse":{"__id__":8}}],"_prefab":{"__type__":"cc.PrefabInfo","root":{"__id__":1},"asset":{"__uuid__":"41lezCW3ZD0Z/j3PDfCB20"},"fileId":"448/nyBaRNDq9udgVuQF5C"},"_contentSize":{"__type__":"cc.Size","width":300,"height":400}},{"__type__":"cc.Node","_name":"spr_prop","_parent":{"__id__":1},"_level":6,"_components":[{"__id__":3}],"_prefab":{"__type__":"cc.PrefabInfo","root":{"__id__":1},"asset":{"__uuid__":"41lezCW3ZD0Z/j3PDfCB20"},"fileId":"574a+8qu9FpoALHZIFV+cv"},"_contentSize":{"__type__":"cc.Size","width":250,"height":250},"_position":{"__type__":"cc.Vec3","x":-1,"y":46.461}},{"__type__":"cc.Sprite","node":{"__id__":2},"_materials":[{"__uuid__":"ecpdLyjvZBwrvm+cedCcQy"}],"_spriteFrame":{"__uuid__":"8c20Sso/ZEn7NUfNSM+EBh"},"_sizeMode":0},{"__type__":"cc.Node","_name":"New Sprite","_parent":{"__id__":1},"_level":6,"_components":[{"__type__":"cc.Sprite","node":{"__id__":4},"_materials":[{"__uuid__":"ecpdLyjvZBwrvm+cedCcQy"}],"_spriteFrame":{"__uuid__":"73e5Bxt3NI7bewZbEaeEj7"}}],"_prefab":{"__type__":"cc.PrefabInfo","root":{"__id__":1},"asset":{"__uuid__":"41lezCW3ZD0Z/j3PDfCB20"},"fileId":"2dmOkzA1xAmq1doVa7/LP/"},"_contentSize":{"__type__":"cc.Size","width":26,"height":28},"_position":{"__type__":"cc.Vec3","x":-118,"y":-170}},{"__type__":"cc.Node","_name":"lbl_price","_parent":{"__id__":1},"_level":6,"_components":[{"__id__":6}],"_prefab":{"__type__":"cc.PrefabInfo","root":{"__id__":1},"asset":{"__uuid__":"41lezCW3ZD0Z/j3PDfCB20"},"fileId":"304SYzmYlF+Ihi9sk5w5NP"},"_color":{"__type__":"cc.Color","r":223,"g":114,"b":32},"_contentSize":{"__type__":"cc.Size","width":12.24,"height":27.72},"_anchorPoint":{"__type__":"cc.Vec2","y":0.5},"_position":{"__type__":"cc.Vec3","x":-97,"y":-170.395}},{"__type__":"cc.Label","node":{"__id__":5},"_materials":[{"__uuid__":"ecpdLyjvZBwrvm+cedCcQy"}],"_useOriginalSize":false,"_string":"0","_N$string":"0","_fontSize":22,"_lineHeight":22,"_N$horizontalAlign":1,"_N$verticalAlign":1},{"__type__":"cc.Node","_name":"lbl_warehouse","_parent":{"__id__":1},"_level":6,"_components":[{"__id__":8}],"_prefab":{"__type__":"cc.PrefabInfo","root":{"__id__":1},"asset":{"__uuid__":"41lezCW3ZD0Z/j3PDfCB20"},"fileId":"f9ZDNDBxNCn7E1Sa8nDqXV"},"_opacity":150,"_color":{"__type__":"cc.Color"},"_contentSize":{"__type__":"cc.Size","width":80,"height":25.2},"_anchorPoint":{"__type__":"cc.Vec2","x":1,"y":0.5},"_position":{"__type__":"cc.Vec3","x":135,"y":-170.395}},{"__type__":"cc.Label","node":{"__id__":7},"_materials":[{"__uuid__":"ecpdLyjvZBwrvm+cedCcQy"}],"_useOriginalSize":false,"_string":"库存充足","_N$string":"库存充足","_fontSize":20,"_lineHeight":20,"_N$horizontalAlign":1,"_N$verticalAlign":1},{"__type__":"cc.Node","_name":"lbl_name","_parent":{"__id__":1},"_level":6,"_components":[{"__id__":10}],"_prefab":{"__type__":"cc.PrefabInfo","root":{"__id__":1},"asset":{"__uuid__":"41lezCW3ZD0Z/j3PDfCB20"},"fileId":"e0bXkZHbpOU4/mvPacDk87"},"_color":{"__type__":"cc.Color"},"_contentSize":{"__type__":"cc.Size","width":180.9,"height":44.1},"_anchorPoint":{"__type__":"cc.Vec2","y":0.5},"_position":{"__type__":"cc.Vec3","x":-131,"y":-117}},{"__type__":"cc.Label","node":{"__id__":9},"_materials":[{"__uuid__":"ecpdLyjvZBwrvm+cedCcQy"}],"_useOriginalSize":false,"_string":"创维55M9S","_N$string":"创维55M9S","_fontSize":35,"_lineHeight":35,"_N$horizontalAlign":1,"_N$verticalAlign":1}],{"__type__":"cc.SpriteFrame","content":{"name":"my_purchase","texture":"2fsfYCe3hPHY4tkSCMRiiM","rect":[0,0,220,72],"offset":[0,0],"originalSize":[220,72],"capInsets":[0,0,0,0]}},{"__type__":"cc.SpriteFrame","content":{"name":"perspective_card","texture":"06o1L4G/tIwrMgB2+L30Yi","rect":[0,0,48,37],"offset":[0,0],"originalSize":[48,37],"capInsets":[0,0,0,0]}},{"__type__":"cc.SpriteFrame","content":{"name":"hone_game_side_but@2x","texture":"62KhEr+wtBspG6ad6qFhio","rect":[0,0,80,57],"offset":[0,0],"originalSize":[80,57],"capInsets":[0,0,0,0]}},{"__type__":"cc.SpriteFrame","content":{"name":"default_scrollbar_vertical","texture":"d608qFRoFHwbXd0Dap056i","rect":[0,0,15,30],"offset":[0,0],"originalSize":[15,30],"capInsets":[4,10,4,10]}},{"__type__":"cc.SpriteFrame","content":{"name":"default_scrollbar_vertical_bg","texture":"61cyPdEfRN047sDK9rO0W5","rect":[0,0,15,30],"offset":[0,0],"originalSize":[15,30],"capInsets":[4,10,4,10]}},{"__type__":"cc.SpriteFrame","content":{"name":"bg@2x","texture":"f5CLy4xeVF/6l9KLLIiqmP","rect":[0,0,750,1334],"offset":[0,0],"originalSize":[750,1334],"capInsets":[0,0,0,0]}},{"__type__":"cc.SpriteFrame","content":{"name":"popup_bj_white","texture":"29+4KdLslAeo5krae5nvJf","rect":[0,0,686,984],"offset":[0,0],"originalSize":[686,984],"capInsets":[0,0,0,0]}},{"__type__":"cc.SpriteFrame","content":{"name":"hone_game_gift@2x","texture":"1eVHc+nMNNvohtIloOIACF","rect":[0,0,76,92],"offset":[0,0],"originalSize":[76,92],"capInsets":[0,0,0,0]}},{"__type__":"cc.SpriteFrame","content":{"name":"my_open@2x","texture":"cbi1ymQadGl71ZC9RkHRox","rect":[0,0,220,72],"offset":[0,0],"originalSize":[220,72],"capInsets":[0,0,0,0]}},{"__type__":"cc.SpriteFrame","content":{"name":"home_but_left@2x","texture":"2crLLvwYROv5EpjS8TegS6","rect":[0,0,157,73],"offset":[0,0],"originalSize":[157,73],"capInsets":[0,0,0,0]}},{"__type__":"cc.SpriteFrame","content":{"name":"my_jelly@2x","texture":"40VNmfYglEP4/eOVcQQOB+","rect":[0,0,26,28],"offset":[0,0],"originalSize":[26,28],"capInsets":[0,0,0,0]}},{"__type__":"cc.SpriteFrame","content":{"name":"hone_game_bg@2x","texture":"b8L7Yy8htAbI3L9UDLmYUB","rect":[0,0,730,1055],"offset":[0,0],"originalSize":[730,1055],"capInsets":[0,0,0,0]}},{"__type__":"cc.SpriteFrame","content":{"name":"home_cancel_but@2x","texture":"71qxuInH9BR4Lr7HT7UKJG","rect":[0,0,220,72],"offset":[0,0],"originalSize":[220,72],"capInsets":[0,0,0,0]}},{"__type__":"cc.SpriteFrame","content":{"name":"perspective_bj","texture":"7aE83XJshIw6jYmdCsqyA6","rect":[0,0,364,64],"offset":[0,0],"originalSize":[364,64],"capInsets":[0,0,0,0]}},{"__type__":"cc.SpriteFrame","content":{"name":"home_perspective_but@2x","texture":"fa0Hv4Uc1LwpFpAuOgnKMZ","rect":[0,0,220,72],"offset":[0,0],"originalSize":[220,72],"capInsets":[0,0,0,0]}},{"__type__":"cc.SpriteFrame","content":{"name":"default_sprite","texture":"6eBWFz0oVHPLIGQKf/9Thu","rect":[0,2,40,36],"offset":[0,0],"originalSize":[40,40],"capInsets":[0,0,0,0]}},{"__type__":"cc.SpriteFrame","content":{"name":"bj","texture":"91IdP2a/BAUZg0U6cPBfp3","rect":[0,0,644,645],"offset":[0,0],"originalSize":[644,645],"capInsets":[0,0,0,0]}},{"__type__":"cc.SpriteFrame","content":{"name":"home_popup_but@2x","texture":"a6khkrh01NCJXTnQKxuqVL","rect":[0,0,190,75],"offset":[0,0],"originalSize":[190,75],"capInsets":[0,0,0,0]}},{"__type__":"cc.SpriteFrame","content":{"name":"default_panel","texture":"d8HsitJHxOYqo801xBk8ev","rect":[0,0,20,20],"offset":[0,0],"originalSize":[20,20],"capInsets":[6,6,6,6]}},{"__type__":"cc.SpriteFrame","content":{"name":"left@2x","texture":"b1bQwQ7E1IQKqDsjvDsbAb","rect":[0,0,36,40],"offset":[0,0],"originalSize":[36,40],"capInsets":[0,0,0,0]}},{"__type__":"cc.SpriteFrame","content":{"name":"hone_game_commodity_bg@2x","texture":"a4XuXpyfRJnrBIKJjgvd37","rect":[0,0,149,148],"offset":[0,0],"originalSize":[149,148],"capInsets":[0,0,0,0]}},{"__type__":"cc.SpriteFrame","content":{"name":"blind_box@2x","texture":"65rBLtCGJHjqmFige9FVAg","rect":[0,0,269,331],"offset":[0,0],"originalSize":[269,331],"capInsets":[0,0,0,0]}},{"__type__":"cc.SpriteFrame","content":{"name":"home_game_block@2x","texture":"6c21NNGghJ6qQZVFZDstoJ","rect":[0,0,616,492],"offset":[0,0],"originalSize":[616,492],"capInsets":[0,0,0,0]}},{"__type__":"cc.SpriteFrame","content":{"name":"close","texture":"63oGMFd2FAL6yw8iklBWpA","rect":[0,0,34,34],"offset":[0,0],"originalSize":[34,34],"capInsets":[0,0,0,0]}},{"__type__":"cc.SpriteFrame","content":{"name":"home_perspective","texture":"caquMnyhFA2Juhj8NKyv7f","rect":[0,0,620,418],"offset":[0,0],"originalSize":[620,418],"capInsets":[0,0,0,0]}},{"__type__":"cc.SpriteFrame","content":{"name":"home_more_but","texture":"7aCpgNOdpCe4JoCjUVFpiE","rect":[0,0,79,97],"offset":[0,0],"originalSize":[79,97],"capInsets":[0,0,0,0]}},{"__type__":"cc.SpriteFrame","content":{"name":"popup_bj","texture":"30Toe5JNRO1ahSLPxypqar","rect":[0,0,200,272],"offset":[0,0],"originalSize":[200,272],"capInsets":[0,0,0,0]}},{"__type__":"cc.SpriteFrame","content":{"name":"my_img_default_bg@2x","texture":"2eTvSOkLlHz4WOOSVGsGO6","rect":[0,0,96,96],"offset":[0,0],"originalSize":[96,96],"capInsets":[0,0,0,0]}},[{"__type__":"cc.Prefab","_name":"BoxItem","data":{"__id__":1}},{"__type__":"cc.Node","_name":"BoxItem","_children":[{"__id__":2}],"_level":1,"_components":[{"__type__":"cc.Sprite","node":{"__id__":1},"_materials":[{"__uuid__":"ecpdLyjvZBwrvm+cedCcQy"}],"_spriteFrame":{"__uuid__":"18aF/7BGtLXLN+EVijKrZK"}},{"__type__":"cc.Button","node":{"__id__":1},"clickEvents":[{"__type__":"cc.ClickEvent","target":{"__id__":1},"_componentId":"83f7c8AnJdJlpAf7yrdN8CG","handler":"onBtnBox"}]},{"__type__":"83f7c8AnJdJlpAf7yrdN8CG","node":{"__id__":1},"box":{"__id__":2},"lblDesc":{"__id__":5}}],"_prefab":{"__type__":"cc.PrefabInfo","root":{"__id__":1},"asset":{"__uuid__":"e121qXN6pMqKoGZmvARduw"},"fileId":"31xxqnszNG/J1rb9bfo6Ak"},"_contentSize":{"__type__":"cc.Size","width":134,"height":134}},{"__type__":"cc.Node","_name":"spr_box","_parent":{"__id__":1},"_children":[{"__id__":3}],"_level":5,"_components":[{"__type__":"cc.Sprite","node":{"__id__":2},"_materials":[{"__uuid__":"ecpdLyjvZBwrvm+cedCcQy"}],"_spriteFrame":{"__uuid__":"62htgpTmdBSoxtjWZ8ATzk"}}],"_prefab":{"__type__":"cc.PrefabInfo","root":{"__id__":1},"asset":{"__uuid__":"e121qXN6pMqKoGZmvARduw"},"fileId":"fawfzLKtxP3oJ2jeimTBQ0"},"_contentSize":{"__type__":"cc.Size","width":76,"height":92},"groupIndex":2},{"__type__":"cc.Node","_name":"New Node","_parent":{"__id__":2},"_children":[{"__id__":4}],"_level":6,"_prefab":{"__type__":"cc.PrefabInfo","root":{"__id__":1},"asset":{"__uuid__":"e121qXN6pMqKoGZmvARduw"},"fileId":"73iZWDnqpJoJBOjJ8yNdd7"},"_position":{"__type__":"cc.Vec3","y":-28}},{"__type__":"cc.Node","_name":"lbl_desc","_parent":{"__id__":3},"_level":3,"_components":[{"__id__":5}],"_prefab":{"__type__":"cc.PrefabInfo","root":{"__id__":1},"asset":{"__uuid__":"e121qXN6pMqKoGZmvARduw"},"fileId":"d6HR8UQm5AOYL+Xt01sWcz"},"_color":{"__type__":"cc.Color"},"_contentSize":{"__type__":"cc.Size","width":124.74,"height":45.199999999999996}},{"__type__":"cc.Label","node":{"__id__":4},"_materials":[{"__uuid__":"ecpdLyjvZBwrvm+cedCcQy"}],"_useOriginalSize":false,"_string":"用户546462正在购买","_N$string":"用户546462正在购买","_fontSize":20,"_lineHeight":20,"_N$horizontalAlign":1,"_N$verticalAlign":1,"_N$overflow":3}],{"__type__":"cc.SpriteFrame","content":{"name":"default_btn_pressed","texture":"b4P/PCArtIdIH38t6mlw8Y","rect":[0,0,40,40],"offset":[0,0],"originalSize":[40,40],"capInsets":[12,12,12,12]}},{"__type__":"cc.SpriteFrame","content":{"name":"hone_game_change@2x","texture":"8eZg8vBkFFKYbjh2KDimAC","rect":[0,0,36,30],"offset":[0,0],"originalSize":[36,30],"capInsets":[0,0,0,0]}},{"__type__":"cc.SpriteFrame","content":{"name":"default_btn_normal","texture":"e8Ueib+qJEhL6mXAHdnwbi","rect":[0,0,40,40],"offset":[0,0],"originalSize":[40,40],"capInsets":[12,12,12,12]}},{"__type__":"cc.SpriteFrame","content":{"name":"home_but_right@2x","texture":"61Tlpc1CtBmaI0jdb0J1gk","rect":[0,0,157,73],"offset":[0,0],"originalSize":[157,73],"capInsets":[0,0,0,0]}},{"__type__":"cc.SpriteFrame","content":{"name":"home_but_middle@2x","texture":"ffB9rTfllCPK6ImyYgxGS2","rect":[0,0,301,95],"offset":[0,0],"originalSize":[301,95],"capInsets":[0,0,0,0]}}]